aserto_idp/__init__.py
aserto_idp/auth0.py
aserto_idp/oidc/__init__.py
aserto_idp/oidc/discovery.py
aserto_idp/oidc/errors.py
aserto_idp/oidc/provider.py
aserto_idp/py.typed
aserto_idp-0.3.1.dist-info/WHEEL
aserto_idp-0.3.1.dist-info/METADATA
aserto_idp-0.3.1.dist-info/RECORD
